{"name":"about @ture7","tagline":"","body":"# about me\r\n**Birthday:** 1995-05-17  \r\n**Place:** Tokyo, Japan  \r\n**Studying at:** The University of Tokyo, College of arts and sciences (Natural Sciences I)  \r\n**Studying:** Java, bash, C/C++, PHP, Linux  \r\n**Belonging to:** [Nonlinear]  \r\n**Hobby:** programming, cycling  \r\n**Like:** Gentoo Linux, vim, bash, Akai Yakusoku (by Veil∞Lia)\r\n\r\n# accounts\r\n* [Bookmeter]: 84435\r\n* [Hatena]: snsw\r\n* [Ask.fm]: turenar\r\n* [twitter]: ture7, ... \r\n* [twilog]: ture7\r\n* [last.fm]: turenai517\r\n* [GitHub]: turenar\r\n* [MusicBrainz]: turenar\r\n* Skype: turenai517\r\n\r\n[Nonlinear]: http://n-linear.org\r\n[Bookmeter]: http://bookmeter.com/u/84435\r\n[Hatena]: http://www.hatena.ne.jp/snsw/\r\n[Ask.fm]: http://ask.fm/turenar\r\n[twitter]: https://twitter.com/ture7\r\n[twilog]: http://twilog.org/ture7\r\n[last.fm]: http://www.lastfm.jp/user/turenai517\r\n[GitHub]: https://github.com/turenar/\r\n[MusicBrainz]: https://musicbrainz.org/user/turenar\r\n\r\n## twitter accounts\r\n\r\n* [Main (@ture7)](https://twitter.com/ture7)\r\n  * [Sub (@ture7n)](https://twitter.com/ture7n) (not for public)\r\n  * Testing Bot (@ture7a)\r\n  * Bot (@misawamaho_bot) (not working)\r\n  * for relatives...\r\n\r\n\r\n## memo\r\n\r\n* 1G: turenai517(→ture7) yurenai517(→ture7l) torenai517(5381) kurenai517(231)\r\n* 2G: ture7 ture7l(2140) ture7s(13821)\r\n* 3G: ture7 ture7n\r\n","google":"","note":"Don't delete this file! It's used internally to help with page regeneration."}